kenzy/VERSION
kenzy/__init__.py
kenzy/__main__.py
kenzy/core.py
kenzy/extras.py
kenzy/run.py
kenzy/settings.py
kenzy/data/__init__.py
kenzy/data/bell.wav
kenzy/data/complete.wav
kenzy/data/prompt.wav
kenzy/data/ready.wav
kenzy/data/ready2.wav
kenzy/image/__init__.py
kenzy/image/__main__.py
kenzy/image/core.py
kenzy/image/device.py
kenzy/image/resources/__init__.py
kenzy/image/resources/mobilenet_v3/__init__.py
kenzy/image/resources/mobilenet_v3/frozen_inference_graph.pb
kenzy/image/resources/mobilenet_v3/labels.txt
kenzy/image/resources/mobilenet_v3/ssd_mobilenet_v3_large_coco_2020_01_14.pbtxt
kenzy/image/resources/yolov7/__init__.py
kenzy/image/resources/yolov7/config.json
kenzy/image/resources/yolov7/labels.txt
kenzy/image/resources/yolov7/yolov7-tiny.pt
kenzy/skillmanager/__init__.py
kenzy/skillmanager/__main__.py
kenzy/skillmanager/core.py
kenzy/skillmanager/device.py
kenzy/stt/__init__.py
kenzy/stt/__main__.py
kenzy/stt/core.py
kenzy/stt/device.py
kenzy/tts/__init__.py
kenzy/tts/__main__.py
kenzy/tts/core.py
kenzy/tts/device.py
kenzy/web/__init__.py
kenzy/web/arrows-rotate-solid.svg
kenzy/web/bars-solid.svg
kenzy/web/bolt-solid.svg
kenzy/web/camera-solid.svg
kenzy/web/circle-info-solid.svg
kenzy/web/dog-solid.svg
kenzy/web/download-solid.svg
kenzy/web/expand-solid.svg
kenzy/web/eye-solid.svg
kenzy/web/favicon.svg
kenzy/web/hdd-solid.svg
kenzy/web/index.html
kenzy/web/jquery.js
kenzy/web/kenzy_touch.png
kenzy/web/lightbulb-solid.svg
kenzy/web/map-pin-solid.svg
kenzy/web/person-walking-solid.svg
kenzy/web/play-solid.svg
kenzy/web/question-circle-solid.svg
kenzy/web/server-solid.svg
kenzy/web/sign-out-alt-solid.svg
kenzy/web/spinner-solid.svg
kenzy/web/stop-solid.svg
kenzy/web/stopwatch-solid.svg
kenzy/web/tachometer-alt.svg
kenzy/web/tools-solid.svg
kenzy/web/upnp.xml
kenzy-2.1.2.dist-info/LICENSE
kenzy-2.1.2.dist-info/METADATA
kenzy-2.1.2.dist-info/WHEEL
kenzy-2.1.2.dist-info/entry_points.txt
kenzy-2.1.2.dist-info/top_level.txt
kenzy-2.1.2.dist-info/zip-safe
kenzy-2.1.2.dist-info/RECORD
