Metadata-Version: 2.1
Name: kenzy
Version: 2.1.2
Summary: Kenzy.Ai: A synthetic human written in Python
Home-page: https://kenzy.ai
Download-URL: https://kenzy.ai/get/latest/release
Author: lnxusr1
Author-email: dist@kenzy.ai
License: MIT
Project-URL: Bug Tracker, https://kenzy.ai/issues
Project-URL: Changelog, https://kenzy.ai/get/latest/changelog
Keywords: Artificial Intelligence,AI,Personal Assistant
Classifier: License :: OSI Approved :: MIT License
Classifier: Programming Language :: Python :: 3
Classifier: Operating System :: OS Independent
Requires-Python: >=3.6
License-File: LICENSE
Requires-Dist: urllib3
Requires-Dist: requests
Requires-Dist: netifaces
